setup.py
acollabauth/__init__.py
acollabauth/backends.py
acollabauth/tests.py
django_acollabauth.egg-info/PKG-INFO
django_acollabauth.egg-info/SOURCES.txt
django_acollabauth.egg-info/dependency_links.txt
django_acollabauth.egg-info/top_level.txt