Metadata-Version: 1.0
Name: django-acollabauth
Version: 0.1
Summary: Automatically create superusers via Active Collab accounts for Django
Home-page: http://jaymz.eu/2011/02/automatic-superusers-via-active-collab-for-django/
Author: Jaymz Campbell
Author-email: jaymz@jaymz.eu
License: UNKNOWN
Platform: UNKNOWN
